indox/__init__.py
indox/indox.py
indox/utils.py
indox/core/__init__.py
indox/core/base_llm.py
indox/core/document_object.py
indox/core/embeddings.py
indox/core/vectorstore.py
indox/data_connectors/__init__.py
indox/data_connectors/arxiv.py
indox/data_connectors/discord.py
indox/data_connectors/github.py
indox/data_connectors/guten.py
indox/data_connectors/twitter.py
indox/data_connectors/wikipedia.py
indox/data_connectors/youtube.py
indox/data_connectors/google/__init__.py
indox/data_connectors/google/googleChat.py
indox/data_connectors/google/googleDoc.py
indox/data_connectors/google/googleDrive.py
indox/data_connectors/google/goolgeSheet.py
indox/data_connectors/google/maps_search.py
indox/data_connectors/utils/__init__.py
indox/data_connectors/utils/document.py
indox/data_loader_splitter/__init__.py
indox/data_loader_splitter/ClusteredSplit/Clustering.py
indox/data_loader_splitter/ClusteredSplit/Embed.py
indox/data_loader_splitter/ClusteredSplit/EmbedClusterSummarize.py
indox/data_loader_splitter/ClusteredSplit/__init__.py
indox/data_loader_splitter/ClusteredSplit/cs_utils.py
indox/data_loader_splitter/ClusteredSplit/split.py
indox/data_loader_splitter/SimpleLoadAndSplit/__init__.py
indox/data_loader_splitter/SimpleLoadAndSplit/loader.py
indox/data_loader_splitter/SimpleLoadAndSplit/split.py
indox/data_loader_splitter/UnstructuredLoadAndSplit/__init__.py
indox/data_loader_splitter/UnstructuredLoadAndSplit/split.py
indox/data_loader_splitter/utils/__init__.py
indox/data_loader_splitter/utils/clean.py
indox/data_loader_splitter/utils/unstructured_utills.py
indox/data_loaders/__init__.py
indox/data_loaders/bs4.py
indox/data_loaders/csv.py
indox/data_loaders/docx.py
indox/data_loaders/excel.py
indox/data_loaders/html.py
indox/data_loaders/joblib.py
indox/data_loaders/json.py
indox/data_loaders/markdown.py
indox/data_loaders/md.py
indox/data_loaders/openpyxl.py
indox/data_loaders/pdfminer.py
indox/data_loaders/pdfplumber.py
indox/data_loaders/pptx.py
Indox-0.1.31.dist-info/LICENSE
Indox-0.1.31.dist-info/METADATA
Indox-0.1.31.dist-info/WHEEL
Indox-0.1.31.dist-info/top_level.txt
Indox-0.1.31.dist-info/RECORD
